{
  "newspaper_id": "newsfirstlk",
  "url": "https://www.newsfirst.lk/2023/04/08/watch-the-cardinal-s-easter-message-exclusively-on-news-1st-and-newsline/",
  "time_ut": 1680934440.0,
  "original_lang": "en",
  "original_title": "Watch the Cardinal\u2019s Easter message. Exclusively on News 1st and Newsline.",
  "original_body_lines": [
    "Colombo (News 1st) \u2013 Watch the Cardinal's Easter message. Exclusively on News 1st and Newsline.",
    "China participating in Sri Lanka\u2019s debt restructuring is a hopeful sign \u2013 US Treasury Secretary",
    "UFC 287: Adesanya knocks out Pereira to get revenge, title back",
    "Still no justice for Easter Attacks, says Cardinal Malcolm Ranjith",
    "Star Wars: New movie to be director by Oscar-winning Pakistani director"
  ]
}