{
  "newspaper_id": "dailyftlk",
  "url": "https://www.ft.lk/business/ISDB-officials-from-Saudi-Arabia-visit-BOI/34-748968",
  "time_ut": 1685565490.0,
  "original_lang": "en",
  "original_title": "ISDB officials from Saudi Arabia visit BOI",
  "original_body_lines": [
    "Islamic Development Bank of Saudi Arabia Islamic Financial Sector Development Department Director Dr. Mohamed Ali Chatti and officials recently met with the Board of Investment Chairman and officials to discuss investment opportunities and the progress of port city Colombo.\u00a0 Colombo Port City Economic Commission member Reyaz Mihular also participated in the discussions."
  ]
}