{
  "newspaper_id": "dailymirrorlk",
  "url": "https://www.dailymirror.lk/breaking_news/Sri-Lanka-wins-silver-in-4x400m-womens-relay/108-263228",
  "time_ut": 1689508530.0,
  "original_lang": "en",
  "original_title": "Sri Lanka wins silver in 4x400m women\u2019s relay",
  "original_body_lines": [
    "The Women\u2019s 4x400m Silver medal was won by Tharushi Karunarathna, Nadeesha Ramanayake, Sayuri Lakshima, and Nishendra Fernando.",
    "They clocked a time of 3:33.27, a Sri Lanka record. Vietnam won first place, while India finished third. (Susil Premalal)"
  ]
}