{
  "newspaper_id": "dailymirrorlk",
  "url": "https://www.dailymirror.lk/top_story/Ven-Rajangane-Saddharathana-Thera-arrested/155-260020",
  "time_ut": 1685332278.0,
  "original_lang": "en",
  "original_title": "Ven. Rajangane Saddharathana Thera arrested",
  "original_body_lines": [
    "Ven. Rajangane Saddharathana Thera, a monk who is famous on social media, has been arrested by the police in the Anuradhapura area.",
    "The Buddhist monk was reportedly arrested following a complaint by Ven. Pahiyangala Ananda Sagara Thero regarding the statements made by Ven. Saddharathana Thera, which are harmful to religious harmony."
  ]
}