{
  "newspaper_id": "adaderanalk",
  "url": "https://www.adaderana.lk/news/88889/tear-gas-fired-at-iusf-protesters-in-colombo",
  "time_ut": 1678186140.0,
  "original_lang": "en",
  "original_title": "Tear gas fired at IUSF protesters in Colombo",
  "original_body_lines": [
    "Police used tear gas and water cannons to disperse protesting university students near the University of Colombo, a short while ago.",
    "The protest march has been organized by the Inter University Students\u2019 Federation (IUSF) based on several demands including the holding of local government elections and the repealing of the Prevention of Terrorism Act (PTA)."
  ]
}