{
  "translated_text": {
    "ta": {
      "title": "\u0bb0\u0bc2\u0baa\u0bbf\u0baf\u0bcb\u0b9f\u0bbf\u0b95\u0bcd \u0b95\u0bc1\u0b95\u0bbf \u0b95\u0bc6\u0bb2\u0bc1 \u0b9a\u0bb5\u0bc1\u0bb2\u0bcd \u0b95\u0bc6\u0ba9\u0bc1\u0b9a\u0bbe \u0bb0\u0bc1\u0bb5\u0bbe\u0ba9\u0bcd. 11 \u0bae\u0bbe\u0ba3\u0bb5\u0bb0\u0bcd",
      "body_lines": [
        "11 \u0bb5\u0baf\u0ba4\u0bc1 \u0b9a\u0bbf\u0bb1\u0bc1\u0bb5\u0ba9\u0bcd 1200 \u0bb0\u0bc2\u0baa\u0bc6\u0b9f\u0bcd \u0b95\u0ba9\u0b9a\u0ba4\u0bc1\u0bb0\u0ba4\u0bcd\u0ba4\u0bc8\u0baa\u0bcd \u0baa\u0baf\u0ba9\u0bcd\u0baa\u0b9f\u0bc1\u0ba4\u0bcd\u0ba4\u0bbf \u0b92\u0bb0\u0bc1 '\u0b9a\u0bcb\u0bb3\u0bae\u0bcd \"\u0b89\u0bb2\u0b95 \u0b9a\u0bbe\u0ba4\u0ba9\u0bc8\u0baf\u0bc8 \u0b89\u0bb0\u0bc1\u0bb5\u0bbe\u0b95\u0bcd\u0b95 \u0bae\u0bc1\u0b9f\u0bbf\u0ba8\u0bcd\u0ba4\u0ba4\u0bc1.",
        "\u0b87\u0ba8\u0bcd\u0ba4 \u0b85\u0bb1\u0bbf\u0b95\u0bcd\u0b95\u0bc8 \u0b95\u0bca\u0bb4\u0bc1\u0bae\u0bcd\u0baa\u0bbf\u0ba9\u0bcd \u0bb0\u0bbe\u0baf\u0bb2\u0bcd \u0b95\u0bb2\u0bcd\u0bb2\u0bc2\u0bb0\u0bbf\u0baf\u0bbf\u0bb2\u0bcd \u0b89\u0bb3\u0bcd\u0bb3 \u0bb0\u0bbe\u0baf\u0bb2\u0bcd \u0b95\u0bb2\u0bcd\u0bb2\u0bc2\u0bb0\u0bbf\u0baf\u0bbf\u0bb2\u0bcd 61 \u00d7 58 \u0bae\u0ba3\u0bbf\u0ba8\u0bc7\u0bb0\u0ba4\u0bcd\u0ba4\u0bc8\u0baa\u0bcd \u0baa\u0baf\u0ba9\u0bcd\u0baa\u0b9f\u0bc1\u0ba4\u0bcd\u0ba4\u0bbf 61 \u00d7 58 \u0bae\u0ba3\u0bbf\u0ba8\u0bc7\u0bb0\u0ba4\u0bcd\u0ba4\u0bc8 \u0b89\u0bb0\u0bc1\u0bb5\u0bbe\u0b95\u0bcd\u0b95\u0bbf\u0baf\u0ba4\u0bc1.",
        "\u0b87\u0ba8\u0bcd\u0ba4 \u0b85\u0bb1\u0bbf\u0b95\u0bcd\u0b95\u0bc8 \u0baf\u0b95\u0bcd\u0b95\u0bb2\u0bbe \u0bb0\u0ba9\u0bb5\u0bbf\u0bb0\u0bc1 \u0b86\u0b9f\u0bc8\u0b95\u0bb3\u0bbf\u0bb2\u0bcd \u0b89\u0bb0\u0bc1\u0bb5\u0bbe\u0b95\u0bcd\u0b95\u0baa\u0bcd\u0baa\u0b9f\u0bcd\u0b9f\u0ba4\u0bc1, \u0b87\u0ba4\u0bc1 \u0b90\u0bb0\u0bcb\u0baa\u0bcd\u0baa\u0bbe \u0b89\u0b9f\u0bcd\u0baa\u0b9f \u0b89\u0bb2\u0b95\u0bbf\u0ba9\u0bcd 26 \u0ba8\u0bbe\u0b9f\u0bc1\u0b95\u0bb3\u0bbf\u0ba9\u0bcd \u0bae\u0bc7\u0bb1\u0bcd\u0baa\u0bbe\u0bb0\u0bcd\u0bb5\u0bc8\u0baf\u0bbf\u0ba9\u0bcd \u0b95\u0bc0\u0bb4\u0bcd \u0b9a\u0bc6\u0baf\u0bcd\u0baf\u0baa\u0bcd\u0baa\u0b9f\u0bcd\u0b9f\u0ba4\u0bc1.",
        "\u0b87\u0bb2\u0b99\u0bcd\u0b95\u0bc8\u0baf\u0bbf\u0ba9\u0bcd (\u0b92\u0bb0\u0bc1 \u0b95\u0bc1\u0bb4\u0ba8\u0bcd\u0ba4\u0bc8) \u0b87\u0bb2\u0b99\u0bcd\u0b95\u0bc8 \u0baa\u0bbe\u0bb5\u0bbf\u0ba9\u0bcd \u0ba4\u0bb2\u0bc8\u0bb5\u0bb0\u0bcd \u0b95\u0bc7\u0baa\u0bcd\u0b9f\u0ba9\u0bcd \u0b87\u0ba8\u0bcd\u0ba4\u0bbf\u0bb0\u0ba8\u0bbe\u0ba4\u0bcd \u0b87\u0ba8\u0bcd\u0ba4\u0bbf\u0bb0\u0ba8\u0bbe\u0ba4\u0bcd \u0b87\u0ba8\u0bcd\u0ba4\u0bbf\u0bb0\u0ba8\u0bbe\u0ba4\u0bcd \u0baa\u0bc6\u0bb0\u0bc7\u0bb0\u0bbe \u0b95\u0bc2\u0bb1\u0bbf\u0ba9\u0bbe\u0bb0\u0bcd:",
        "\u0b9c\u0bc6\u0bb0\u0bcd\u0bae\u0ba9\u0bbf\u0baf\u0bbf\u0ba9\u0bcd \u0b87\u0bb2\u0b99\u0bcd\u0b95\u0bc8 \u0b95\u0bbf\u0bb3\u0bc8\u0baf\u0bbf\u0ba9\u0bcd \u0ba4\u0bb2\u0bc8\u0bb5\u0bb0\u0bbe\u0ba9 \u0b87\u0bb2\u0b99\u0bcd\u0b95\u0bc8 \u0b95\u0bbf\u0bb3\u0bc8\u0ba4\u0bcd \u0ba4\u0bb2\u0bc8\u0bb5\u0bb0\u0bcd \u0b95\u0baa\u0bb0\u0ba9\u0bcd\u0bb8\u0bcd \u0b9a\u0bbe\u0bae\u0bc1\u0bb5\u0bc7\u0bb2\u0bcd, \u0b89\u0bb2\u0b95 \u0baa\u0bc1\u0ba4\u0bcd\u0ba4\u0b95\u0ba4\u0bcd\u0ba4\u0bbf\u0ba9\u0bcd \u0b95\u0baa\u0bb2\u0bbe\u0ba9\u0bbf \u0bb0\u0bbe\u0b9c\u0bbe\u0bb5\u0bbf\u0ba9\u0bcd \u0b9a\u0bbe\u0b95\u0bcd \u0baa\u0bc1\u0ba4\u0bcd\u0ba4\u0b95\u0ba4\u0bcd\u0ba4\u0bbf\u0ba9\u0bcd \u0ba4\u0bc1\u0ba3\u0bc8\u0ba4\u0bcd \u0ba4\u0bb2\u0bc8\u0bb5\u0bb0\u0bbf\u0ba9\u0bcd \u0b89\u0bb2\u0b95\u0bb3\u0bbe\u0bb5\u0bbf\u0baf \u0b85\u0bb1\u0bbf\u0b95\u0bcd\u0b95\u0bc8\u0baf\u0bc8 \u0ba8\u0bbf\u0bb1\u0bc1\u0bb5\u0bbf\u0baf\u0ba4\u0bc8 \u0b89\u0bb0\u0bc1\u0bb5\u0bbe\u0b95\u0bcd\u0b95\u0bbf\u0baf\u0ba4\u0bc1 \u0bb5\u0bbf\u0ba9\u0bcd\u0bb8\u0bcd \u0b9a\u0bc0\u0baa\u0bcd\u0bb3\u0bc7\u0ba9\u0bcd \u0b8e\u0ba9\u0bcd\u0bb1\u0bc1 \u0baa\u0bc6\u0baf\u0bb0\u0bbf\u0b9f\u0baa\u0bcd\u0baa\u0b9f\u0bcd\u0b9f\u0ba4\u0bc1.",
        "\u0baa\u0bb4\u0bae\u0bc8\u0baf\u0bbe\u0ba9 \u0b95\u0bc1\u0bb4\u0ba8\u0bcd\u0ba4\u0bc8, \u0b85\u0bae\u0bc1\u0ba9\u0bc1\u0b95\u0bcb\u0b9f\u0bbe \u0b95\u0bc1\u0bb4\u0ba8\u0bcd\u0ba4\u0bc8, \u0b95\u0bca\u0bb4\u0bc1\u0bae\u0bcd\u0baa\u0bbf\u0ba9\u0bcd \u0bb0\u0bbe\u0baf\u0bb2\u0bcd \u0b95\u0bb2\u0bcd\u0bb2\u0bc2\u0bb0\u0bbf\u0baf\u0bbf\u0bb2\u0bcd \u0b90\u0ba8\u0bcd\u0ba4\u0bc1 \u0bb0\u0ba9\u0bcd\u0b95\u0bb3\u0bbf\u0bb2\u0bcd \u0b9a\u0bc7\u0bb0\u0bcd\u0b95\u0bcd\u0b95\u0baa\u0bcd\u0baa\u0b9f\u0bcd\u0b9f\u0bc1\u0bb3\u0bcd\u0bb3\u0ba4\u0bc1.",
        "\u0b95\u0bc1\u0bb4\u0ba8\u0bcd\u0ba4\u0bc8\u0baf\u0bbf\u0ba9\u0bcd \u0ba4\u0ba8\u0bcd\u0ba4\u0bc8 \u0b9a\u0bb8\u0bcd\u0ba9\u0bc1\u0bb2\u0bbe, \u0b95\u0bc1\u0bb4\u0ba8\u0bcd\u0ba4\u0bc8\u0baf\u0bbf\u0ba9\u0bcd \u0ba4\u0ba8\u0bcd\u0ba4\u0bc8 \u0ba4\u0ba8\u0bcd\u0ba4\u0bbf\u0bb0\u0bae\u0bbe\u0ba9 \u0bb2\u0b95\u0bcd\u0bae\u0bbe\u0bb2\u0bcd, \u0b95\u0bc1\u0bb4\u0ba8\u0bcd\u0ba4\u0bc8\u0baf\u0bbf\u0ba9\u0bcd \u0ba4\u0ba8\u0bcd\u0ba4\u0bc8 \u0ba4\u0ba8\u0bcd\u0ba4\u0bbf\u0bb0\u0bae\u0bbe\u0ba9 \u0bb2\u0b95\u0bcd\u0bae\u0bb2\u0bcd \u0b86\u0b95\u0bbf\u0baf\u0bcb\u0bb0\u0bcd \u0b92\u0ba9\u0bcd\u0bb1\u0bbe\u0b95 \u0b87\u0bb0\u0bc1\u0ba8\u0bcd\u0ba4\u0ba9\u0bb0\u0bcd."
      ]
    },
    "en": {
      "title": "Reubiotic Cuki Kelu Saule Kenusa Ruwan. 11 student",
      "body_lines": [
        "The 11-year-old boy was able to create a 'Cholan \"world record using 1200 Rubet Cube.",
        "The report was placed in the Royal College, Royal College, Colombo, creating a 61 \u00d7 58 hours using a 61 \u00d7 58 hours.",
        "The report was created in the Yakkala Ranaviru Apparel and this was done under the supervision of 26 countries in the world, including Europe.",
        "Captain Indranath Indranath Indranath Perera, chairman of the Sri Lankan Bau of the Sri Lanka (A child), said:",
        "The creation of the establishment of a global report by the Vice President of the Chock Book of World Book Kapunani Raja, Sri Lanka Branch Chairman Kaparans Samuel, Chairman of the Sri Lanka Branch of Germany, were named Vince Seaplane.",
        "The oldest child, Amunugoda child, has been included in Royal College, Colombo five runs.",
        "Sasnula composed the Sasnula, the father of the child, Tricky Lakmal, the father of the child, Tricky Lakmal, the father of the child, is Ms. Deepika Kumari.Family members were together."
      ]
    }
  },
  "summary_lines": [
    "Here's a summary of the text in approximately 200 characters:",
    "",
    "11-year-old boy sets Rubik's Cube world record at Royal College, Colombo. Creates 61x58-hour report under international supervision. Parents and family members present."
  ]
}