{
  "translated_text": {
    "si": {
      "title": "\u0d89\u0dad\u0dd2\u0dc4\u0dcf\u0dc3\u0dba \u0db4\u0dd9\u0dbb\u0dc5\u0dd3\u0db8\u0daf?",
      "body_lines": [
        "1972 \u0daf\u0dd3 \u0da2\u0dd3.\u0da2\u0dd3."
      ]
    },
    "en": {
      "title": "Is history twist?",
      "body_lines": [
        "In 1972, GG Ponnambalam went to the residence of SJV Selvanayagam and created a strong Tamil United Front - Gajendrakumar - Sridharan's meeting historyThe most important is a milestone."
      ]
    }
  },
  "summary_lines": [
    "Here's a summary of 200 characters:",
    "",
    "History twist: In 1972, GG Ponnambalam formed a strong Tamil United Front. This event marked a significant milestone in political history."
  ]
}