{
  "translated_text": {
    "si": {
      "title": "\u0da2\u0dd3\u0dc0 \u0dbb\u0dd4\u0db0\u0dd2\u0dbb\u0dba \u0db4\u0dc4\u0dbb\u0daf\u0dd3\u0db8 \u0dc3\u0dd2\u0daf\u0dd4 \u0dc0\u0dd6 \u0dc0\u0dd2\u0da7 - \u0d91\u0d9a\u0dca\u0dc3\u0dad\u0dca \u0da2\u0db1\u0dad\u0dcf \u0db6\u0dbd\u0dba\u0dda \u0db4\u0dca\u0dbb\u0dc1\u0dca\u0db1\u0dba \u0dc0\u0dd6 \u0dc3\u0d82\u0d9b\u0dd2\u0dbb\u0dd2\u0dbd\u0dcf \u0dc4\u0ddd\u0da7\u0dbd\u0dba\u0dda \u0d9a\u0dcf\u0db8\u0dbb 616 \u0dc3\u0dd2\u0da7 623 \u0daf\u0d9a\u0dca\u0dc0\u0dcf \u0dbb\u0dd0\u0db3\u0dd3 \u0dc3\u0dd2\u0da7\u0dd2 \u0d85\u0dba?",
      "body_lines": [
        "\u0d91\u0d9a\u0dca\u0dc3\u0dad\u0dca \u0da2\u0db1\u0dad\u0dcf \u0db6\u0dbd\u0dc1\u0d9a\u0dca\u0dad\u0dd2\u0dba 616 \u0dc3\u0dc4 623 \u0dc0\u0db1 \u0d9a\u0dcf\u0db8\u0dbb\u0dc0\u0dbd \u0db1\u0dd0\u0dc0\u0dad\u0dd3 \u0dc3\u0dd2\u0da7\u0dd2 \u0d85\u0dad\u0dbb \u0d94\u0dc4\u0dd4 \u0db1\u0dc0\u0dcf\u0dad\u0dd0\u0db1\u0dca \u0d9c\u0dd9\u0db1 \u0dc3\u0dd2\u0da7\u0dd2 \u0d85\u0dad\u0dbb \u0dc3\u0dc4\u0dbb\u0dcf\u0db1\u0dca \u0dc4\u0dc2\u0dd3\u0db8\u0dca \u0db8\u0dc4\u0dad\u0dcf \u0dc3\u0d82\u0d9c\u0dd2\u0dbd\u0dcf \u0dc4\u0ddd\u0da7\u0dbd\u0dba\u0dda \u0dbb\u0dd0\u0db3\u0dd3 \u0dc3\u0dd2\u0da7\u0dd2\u0dba\u0dda\u0dba.",
        "2019 \u0d85\u0db4\u0dca\u0dbb\u0dda\u0dbd\u0dca 21 \u0dc0\u0db1 \u0daf\u0dd2\u0db1 \u0db8\u0dbb\u0dcf\u0d9c\u0dd9\u0db1 \u0db8\u0dd0\u0dbb\u0dd9\u0db1 \u0db4\u0dca\u0dbb\u0dc4\u0dcf\u0dbb\u0dba\u0da7 \u0dc3\u0db8\u0dca\u0db6\u0db1\u0dca\u0db0 \u0dc3\u0dc4 \u0d94\u0dc4\u0dd4\u0d9c\u0dda \u0dc3\u0d9a\u0dcf\u0db1\u0dca \u0dc4\u0dba\u0dd2\u0db8\u0dca \u0dc3\u0dc4 \u0d94\u0dc4\u0dd4\u0d9c\u0dda \u0dc3\u0d9a\u0dcf \u0d89\u0dbd\u0dcf\u0dc3\u0dd2\u0db8\u0dca \u0dc3\u0dc4 \u0d94\u0dc4\u0dd4\u0d9c\u0dda \u0dc3\u0d9a\u0dcf \u0d89\u0dbd\u0dcf\u0db8\u0dca \u0d85\u0dc4\u0db8\u0daf\u0dca, 20 \u0dc0\u0db1 \u0daf\u0dd2\u0db1 \u0d91\u0db8 \u0dc4\u0ddd\u0da7\u0dbd\u0dba\u0dda\u0daf\u0dd3 \u0dbb\u0dd0\u0dc3\u0dca\u0dc0\u0dd6 \u0da2\u0db1\u0dad\u0dcf\u0dc0\u0d9c\u0dda \u0dad\u0ddc\u0dbb\u0dad\u0dd4\u0dbb\u0dd4 \u0d85\u0db4 \u0dc0\u0dd2\u0dc3\u0dd2\u0db1\u0dca \u0dc0\u0dc3\u0db1\u0dca \u0d9a\u0dd2\u0dbb\u0dd3\u0db8\u0da7 \u0d8b\u0dad\u0dca\u0dc3\u0dcf\u0dc4 \u0d9a\u0dbb\u0db1 \u0db6\u0dc0 \u0d91\u0d9a\u0dca\u0dc3\u0dad\u0dca \u0da2\u0db1\u0dad\u0dcf \u0db6\u0dbd\u0dc0\u0dda\u0d9c\u0dba \u0dc0\u0dcf\u0dbb\u0dca\u0dad\u0dcf \u0dc0\u0dd3 \u0dad\u0dd2\u0db6\u0dda.",
        "\u0d91\u0d9a\u0dca\u0dc3\u0dad\u0dca \u0da2\u0db1\u0dad\u0dcf \u0db6\u0dbd\u0dc1\u0d9a\u0dca\u0dad\u0dd2 \u0db4\u0dca\u0dbb\u0d9a\u0dcf\u0dc1\u0d9a \u0db8\u0dd4\u0da2\u0dd2\u0db6\u0dbb\u0dca \u0dbb\u0dc4\u0dca\u0db8\u0dcf\u0db1\u0dca \u0dad\u0ddc\u0dbb\u0dad\u0dd4\u0dbb\u0dd4 \u0db1\u0dd2\u0d9a\u0dd4\u0dad\u0dca \u0d9a\u0dbb \u0dad\u0dd2\u0db6\u0dda.",
        "2019 \u0d85\u0db4\u0dda\u0dca\u0dbb\u0dbd\u0dca 20 \u0dc0\u0db1 \u0daf\u0dd2\u0db1 \u0dbb\u0dcf\u0dad\u0dca\u0dbb\u0dd2\u0dba\u0dda \u0dc3\u0d82\u0d9c\u0dd2\u0dbb\u0dd4\u0dc0\u0dbd \u0dc4\u0ddd\u0da7\u0dbd\u0dba\u0dda \u0dc4\u0dba\u0dc0\u0db1 \u0db8\u0dc4\u0dbd\u0dda \u0db4\u0dd2\u0dc4\u0dd2\u0da7\u0dd2 \u0dc3\u0dd2\u0dba\u0daf\u0dd2\u0dc0\u0dd2 \u0db1\u0dc3\u0dcf\u0d9c\u0dd0\u0db1\u0dd3\u0db8\u0dda \u0db6\u0ddd\u0db8\u0dca\u0db6 \u0daf\u0dd9\u0d9a\u0d9a\u0dca \u0d9a\u0dcf\u0db8\u0dbb\u0dba\u0dda \u0dbb\u0dd0\u0db3\u0dd3 \u0dc3\u0dd2\u0da7\u0dd2\u0dba\u0dda\u0dba.",
        "\u0d9a\u0dcf\u0db8\u0dbb\u0dba\u0dda \u0db1\u0dd0\u0dc0\u0dad\u0dd3 \u0dc3\u0dd2\u0da7\u0dd2 \u0db8\u0dd2\u0db1\u0dd2\u0dc3\u0dd4\u0db1\u0dca \u0daf\u0dd9\u0daf\u0dd9\u0db1\u0dcf\u0d9c\u0dda \u0db1\u0db8\u0dca \u0dc3\u0dd0\u0d9a\u0dc3\u0dd3\u0db8 \u0dc4\u0ddd\u0da7\u0dbd\u0dca \u0d9a\u0dc5\u0db8\u0db1\u0dcf\u0d9a\u0dbb\u0dab\u0dba \u0db4\u0dca\u0dbb\u0dad\u0dd2\u0d9a\u0dca\u0dc2\u0dda\u0db4 \u0d9a\u0dbb\u0db1 \u0db6\u0dc0 \u0daf \u0d94\u0dc4\u0dd4 \u0db4\u0dd0\u0dc0\u0dc3\u0dd3\u0dba.",
        "\u0daf\u0dd2\u0dc0\u0dd2 \u0d9c\u0dbd\u0dc0\u0dcf \u0d9c\u0dad\u0dca \u0db4\u0dc5\u0db8\u0dd4 \u0dc3\u0dad\u0dd2 \u0daf\u0dd9\u0d9a \u0dad\u0dd4\u0dc5 \u0dc4\u0ddd\u0da7\u0dbd\u0dba\u0dda \u0dbb\u0dd0\u0db3\u0dd3 \u0dc3\u0dd2\u0da7\u0dd2 \u0d85\u0dba\u0d9c\u0dda \u0dad\u0ddc\u0dbb\u0dad\u0dd4\u0dbb\u0dd4 \u0d9a\u0ddc\u0dc5\u0db9 \u0db8\u0dc4\u0dcf\u0db0\u0dd2\u0d9a\u0dbb\u0dab\u0dba\u0da7 \u0db7\u0dcf\u0dbb \u0daf\u0dd4\u0db1\u0dca \u0db1\u0db8\u0dd4\u0dad\u0dca \u0dc4\u0ddd\u0da7\u0dbd\u0dca \u0d9a\u0dc5\u0db8\u0db1\u0dcf\u0d9a\u0dcf\u0dbb\u0dd2\u0dad\u0dca\u0dc0\u0dba 616 \u0dc0\u0db1 \u0d9a\u0dcf\u0db8\u0dbb\u0dba\u0dda \u0db1\u0dd0\u0dc0\u0dad\u0dd3 \u0dc3\u0dd2\u0da7\u0dd2 \u0d85\u0dba \u0db4\u0dd2\u0dc5\u0dd2\u0db6\u0db3 \u0dad\u0ddc\u0dbb\u0dad\u0dd4\u0dbb\u0dd4 \u0dbd\u0db6\u0dcf \u0daf\u0dd3 \u0db1\u0dd0\u0dad.",
        "\u0db8\u0dd4\u0da2\u0dd2\u0db6\u0dbb\u0dca \u0dbb\u0dc4\u0dca\u0db8\u0dcf\u0db1\u0dca \u0d9a\u0dd2\u0dba\u0dcf \u0dc3\u0dd2\u0da7\u0dd2\u0dba\u0dda \u0dc4\u0ddd\u0da7\u0dbd\u0dca \u0db4\u0dbb\u0dd2\u0db4\u0dcf\u0dbd\u0db1\u0dba \u0dc4\u0ddd\u0da7\u0dbd\u0dba\u0dda \u0d85\u0db1\u0dd9\u0d9a\u0dca \u0d9a\u0dcf\u0db8\u0dbb\u0dba\u0dda \u0dc4\u0ddd\u0da7\u0dbd\u0dba\u0dda \u0d85\u0db0\u0dd2\u0d9a\u0dbb\u0dab\u0dba\u0da7 \u0dc0\u0dcf\u0dbb\u0dca\u0dad\u0dcf \u0db1\u0ddc\u0d9a\u0dc5 \u0db6\u0dc0\u0dad\u0dca \u0d9a\u0dd2\u0dba\u0dcf \u0dc3\u0dd2\u0da7\u0dd2\u0dba\u0dda \u0dc3\u0dc4\u0dbb\u0dcf\u0db1\u0dca \u0dc4\u0dc2\u0dd3\u0db8\u0dca\u0d9c\u0dda \u0d9a\u0dab\u0dca\u0da9\u0dcf\u0dba\u0db8 \u0dc3\u0dc4\u0dbb\u0dcf\u0db1\u0dca \u0dc4\u0dc2\u0dd3\u0db8\u0dca \u0d9a\u0dab\u0dca\u0da9\u0dcf\u0dba\u0db8 \u0dc3\u0db8\u0d9f \u0dc3\u0db8\u0dca\u0db6\u0db1\u0dca\u0db0 \u0dc0\u0dd3 \u0d87\u0dad\u0dd2 \u0db6\u0dc0\u0dba\u0dd2."
      ]
    },
    "en": {
      "title": "Who stayed in the 616- 623 number of rooms at the Sankirila Hotel when the lifeblood attack took place- the United People's Power Question?",
      "body_lines": [
        "The United People's Power has questioned who was staying in the 616 and 623rd rooms while Sahran Hashim was staying at the Sangirila Hotel.",
        "The United People's Power has reported that Sahran Hassim and his Saka Ilam Ahmad, who were involved in the suicide attack on April 21, 2019, are trying to cover up the details of the people who met at the same hotel on the 20th.",
        "United People's Power spokesman Mujibur Rahman has released the information.",
        "On the night of April 20, 2019, two suicide bombs were staying in the room on the sixth floor of the Sangirila Hotel.",
        "He also said that the hotel management refuses to make the names of the two men who stayed in the room.",
        "He said that the details of those who stayed at the hotel in the first two weeks of the survival Sunday attack were handed over to the Colombo High Court, but the hotel management did not provide details of those who stayed in the 616th room.",
        "Mujibur Rahman said that the hotel administration did not report to the court of the hotel in the other room of the hotel, and said that the Sahran Hashim's team appeared to be associated with the Sahran Hashim group."
      ]
    }
  },
  "summary_lines": [
    "The United People's Power has questioned who stayed in the 616 and 623rd rooms at the Sangirila Hotel during the lifeblood attack, where Sahran Hashim was present. The group alleges that Sahran Hashim and Saka Ilam Ahmad, involved in the suicide attack, are trying to hide details of the hotel's guests. The hotel management has refused to disclose the names of the two men in the 616th room, despite handing over details of other guests to the Colombo High Court."
  ]
}