{
  "newspaper_id": "dailyftlk",
  "url": "https://www.ft.lk/news/Ravi-Seneviratne-appointed-as-Public-Security-Ministry-Secretary/56-767072",
  "time_ut": 1727129358.0,
  "original_lang": "en",
  "original_title": "Ravi Seneviratne appointed as Public Security Ministry Secretary",
  "original_body_lines": [
    "The newly-elected President Anura Kumara Dissanayake yesterday appointed former Senior Deputy Inspector General (DIG) Ravi Seneviratne as the Public Security Ministry Secretary.",
    "Seneviratne, a retired Senior Deputy Inspector General of Police, holds a Master\u2019s Degree in Human Rights from the University of Colombo. He has served as a founding member of the Special Task Force (STF), former Deputy Director of the State Intelligence Service (SIS), First Secretary of the Sri Lanka Embassy in Thailand, and the Head of Sri Lanka Interpol Sri Lanka."
  ]
}