{
  "newspaper_id": "economynextcom",
  "url": "https://economynext.com/sri-lanka-stock-index-tops-20000-points-rupee-steady-234430/",
  "time_ut": 1754280240.0,
  "original_lang": "en",
  "original_title": "Sri Lanka stock index tops 20,000 points, rupee steady",
  "original_body_lines": [
    "ECONOMYNEXT \u2013 Sri Lanka benchmark Colombo All Share Index topped, 20,000 points, rising 99 points in early trade, provisional stock exchange data showed, and the rupee was flat, dealers said.",
    "Sri Lanka\u2019s rupee opened at 301.10/22 to the US dollar in the spot market Monday, relatively flat from 301.20/30 the previous day, while bond yields held broadly steady, dealers said.",
    "The telegraphic transfer rates were: euro buying 342.332 selling 353.5380, British pound buying 394.2796 selling 405.6214, American dollar buying 297.7500 selling 304.7500.",
    "A bond maturing on 15.10.2028 was quoted at 8.85/90 percent, up from 8.75/85 percent.",
    "A bond maturing on 15.12.2029 was quoted at 9.40/43 percent, up rom 9.35/40 percent.",
    "A bond maturing on 15.03.2031 was quoted at 9.85/95 percent.",
    "A bond maturing on 15.12.2032 was quoted at 10.25/30 percent, from 10.23/26 percent. (Colombo/Aug4/2025)"
  ]
}