{
  "newspaper_id": "dailymirrorlk",
  "url": "https://www.dailymirror.lk/caption-story/Against-privatising-Govt-institutions/110-282659",
  "time_ut": 1715784960.0,
  "original_lang": "en",
  "original_title": "Against privatising Govt. institutions",
  "original_body_lines": [
    "A protest was held in front of the Fort Railway station against the government privatising government institutions, including Telecom, Insurance and Milco. The protesters also demanded that the government abolish the Electricity Act, which will become a huge burden to the public. Pix by Pradeep Dilrukshana"
  ]
}