{
  "newspaper_id": "adaderanalk",
  "url": "https://www.adaderana.lk/news/110900/thilini-priyamali-arrested",
  "time_ut": 1753676520.0,
  "original_lang": "en",
  "original_title": "Thilini Priyamali arrested",
  "original_body_lines": [
    "Businesswoman Thilini Priyamali has been arrested by the Homagama Police today (28).",
    "She has been apprehended on several charges, including obstructing the duties of a fiscal officer at the Homagama Magistrate\u2019s Court, said Ada Derana reporter.",
    "Priyamali was taken into custody after arriving at the police station in compliance with a court order requiring her to provide a statement to police.",
    "Businesswoman Thilini Priyamali, was previously arrested and remanded for allegedly committing massive financial fraud."
  ]
}