{
  "newspaper_id": "newsfirstlk",
  "url": "https://english.newsfirst.lk/2025/10/05/drug-raids-lead-to-seven-arrests-in-south-two-arrested-in-polonnaruwa-for-selling-ice",
  "time_ut": 1759657920.0,
  "original_lang": "en",
  "original_title": "Drug Raids Lead To Seven Arrests In South, Two Arrested In Polonnaruwa For Selling Ice",
  "original_body_lines": [
    "COLOMBO (News 1st); Seven suspects have been arrested with Hash and ice narcotics in Baddegama, Habaraduwa, and Midigama areas.The arrests were made, during raids conducted by the Matara and Hambantota Divisional Crime Units based on a tip off received.\u00a0Over 5 kilograms of Hash were found in suspect's possession.\u00a0Meanwhile, two individuals involved in selling ice narcotics were arrested, in Katuwanwila area of,Welikanda, Polonnaruwa.\u00a0Police seized several packets of ice drugs along with cash amounting to approximately Rs. 70,000 during arrest.\u00a0The suspects are reportedly residents of the area."
  ]
}