{
  "newspaper_id": "economynextcom",
  "url": "https://economynext.com/election-commissioner-urges-sri-lankans-to-vote-early-187543/",
  "time_ut": 1731567420.0,
  "original_lang": "en",
  "original_title": "Election Commissioner urges Sri Lankans to vote early",
  "original_body_lines": [
    "ECONOMYNEXT \u2013 Sri Lanka\u2019s Commissioner General of Elections Saman Sri Ratnayake urged voters to show up and vote in the ongoing general election.",
    "\u201cWe ask that all eligible voters to go to their polling stations as soon as possible,\u201d Ratnayake told reporters.",
    "Other officials urged citizens to vote while the weather was still favourable, with rains expected later in the day.",
    "Polls will close at 4 pm, after which Ratnayake said, counting will begin at 5 pm.",
    "\u201cI believe we will  be able to announce the first results by 10 pm, and regularly thereafter.\u201d",
    "Sri Lanka is voting to choose 225 members to its legislature."
  ]
}